{
    "Type": "SLABL",
    "graphic": "Polygon",
    "width": 150,
    "height": 150,
    "basicPoint": {
        "x": 0,
        "y": 0
    },
    "polygonNodes": [
        {
            "x": 0,
            "y": 0
        },
        {
            "x": 150,
            "y": 0
        },
        {
            "x": 150,
            "y": 150
        },
        {
            "x": 0,
            "y": 150
        }
    ],
    "PinLayout": [
        {
            "Type": "circle_pin",
            "Name": "A",
            "pos": {
                "x": 0,
                "y": 75
            }
        },
        {
            "Type": "circle_pin",
            "Name": "OA",
            "pos": {
                "x": 150,
                "y": 75
            }
        }
    ],
    "insideLayout": [
        {
            "Type": "LUT",
            "Name": "LUTA",
            "pos": {
                "x": 10,
                "y": 15
            }
        },
        {
            "Type": "LUT",
            "Name": "LUTB",
            "pos": {
                "x": 10,
                "y": 30
            }
        },
        {
            "Type": "LUT",
            "Name": "LUTC",
            "pos": {
                "x": 10,
                "y": 45
            }
        },
        {
            "Type": "LUT",
            "Name": "LUTD",
            "pos": {
                "x": 10,
                "y": 60
            }
        },
        {
            "Type": "LUT",
            "Name": "LUTE",
            "pos": {
                "x": 10,
                "y": 80
            }
        },
        {
            "Type": "LUT",
            "Name": "LUTF",
            "pos": {
                "x": 10,
                "y": 95
            }
        },
        {
            "Type": "LUT",
            "Name": "LUTG",
            "pos": {
                "x": 10,
                "y": 110
            }
        },
        {
            "Type": "LUT",
            "Name": "LUTH",
            "pos": {
                "x": 10,
                "y": 125
            }
        },
        {
            "Type": "MUX2",
            "Name": "MUX2FF",
            "pos": {
                "x": 30,
                "y": 25
            }
        },
        {
            "Type": "MUX2",
            "Name": "MUX2FF",
            "pos": {
                "x": 30,
                "y": 60
            }
        },
        {
            "Type": "MUX2",
            "Name": "MUX2FF",
            "pos": {
                "x": 30,
                "y": 95
            }
        },
        {
            "Type": "MUX2",
            "Name": "MUX2FF",
            "pos": {
                "x": 30,
                "y": 130
            }
        },
        {
            "Type": "MUX2",
            "Name": "MUX2FF",
            "pos": {
                "x": 45,
                "y": 40
            }
        },
        {
            "Type": "MUX2",
            "Name": "MUX2FF",
            "pos": {
                "x": 45,
                "y": 110
            }
        },
        {
            "Type": "MUX2",
            "Name": "MUX2FF",
            "pos": {
                "x": 60,
                "y": 73
            }
        },
        {
            "Type": "CLA",
            "Name": "CLA0",
            "pos": {
                "x": 80,
                "y": 25
            },
            "rotation": 90
        },
        {
            "Type": "CLA",
            "Name": "CLA1",
            "pos": {
                "x": 80,
                "y": 97
            }
        },
        {
            "Type": "MUX4",
            "Name": "MUX4ff",
            "pos": {
                "x": 100,
                "y": 100
            }
        },
        {
            "Type": "MUX4",
            "Name": "MUX4ff",
            "pos": {
                "x": 100,
                "y": 104
            }
        },
        {
            "Type": "MUX4",
            "Name": "MUX4ff",
            "pos": {
                "x": 100,
                "y": 108
            }
        },
        {
            "Type": "MUX4",
            "Name": "MUX4ff",
            "pos": {
                "x": 100,
                "y": 112
            }
        }
    ]
}